py2bit.cpython-311-x86_64-linux-gnu.so
py2bitTest/test.py
py2bitTest/__init__.py
py2bitTest/foo.2bit
py2bit-0.3.3.dist-info/METADATA
py2bit-0.3.3.dist-info/RECORD
py2bit-0.3.3.dist-info/top_level.txt
py2bit-0.3.3.dist-info/WHEEL
py2bit-0.3.3.dist-info/LICENSE.txt
