Metadata-Version: 2.2
Name: py2bit
Version: 0.3.3
Summary: A package for accessing 2bit files using lib2bit
Author-email: "Devon P. Ryan" <dpryan79@gmail.com>
License: MIT
Project-URL: download, https://github.com/deeptools/py2bit
Project-URL: homepage, https://github.com/deeptools/py2bit
Keywords: bioinformatics,2bit
Classifier: Development Status :: 5 - Production/Stable
Classifier: Intended Audience :: Developers
Classifier: License :: OSI Approved
Classifier: Programming Language :: C
Classifier: Programming Language :: Python
Classifier: Programming Language :: Python :: 2.7
Classifier: Programming Language :: Python :: 3
Classifier: Programming Language :: Python :: Implementation :: CPython
Classifier: Operating System :: POSIX
Classifier: Operating System :: Unix
Classifier: Operating System :: MacOS
License-File: LICENSE.txt
